README.md
setup.py
budgettracker/__init__.py
budgettracker/__main__.py
budgettracker/budget.py
budgettracker/categories.py
budgettracker/cli.py
budgettracker/data.py
budgettracker/helpers.py
budgettracker/storage.py
budgettracker.egg-info/PKG-INFO
budgettracker.egg-info/SOURCES.txt
budgettracker.egg-info/dependency_links.txt
budgettracker.egg-info/entry_points.txt
budgettracker.egg-info/not-zip-safe
budgettracker.egg-info/requires.txt
budgettracker.egg-info/top_level.txt
budgettracker/bank_adapters/__init__.py
budgettracker/bank_adapters/bankin.py
budgettracker/bank_adapters/base.py
budgettracker/bank_adapters/csv.py
budgettracker/bank_adapters/multi.py
budgettracker/bank_adapters/ofx.py
budgettracker/notify_adapters/__init__.py
budgettracker/notify_adapters/bouygues_telecom_sms.py
budgettracker/notify_adapters/email.py
budgettracker/web/__init__.py
budgettracker/web/static/chartist.min.css
budgettracker/web/static/chartist.min.js
budgettracker/web/static/icon.png
budgettracker/web/static/jscolor.min.js
budgettracker/web/static/main.js
budgettracker/web/static/style.css
budgettracker/web/templates/_budget.html
budgettracker/web/templates/_categories_bar.html
budgettracker/web/templates/_month_switcher.html
budgettracker/web/templates/_tx_options.html
budgettracker/web/templates/_year_overview.html
budgettracker/web/templates/category.html
budgettracker/web/templates/goal.html
budgettracker/web/templates/index.html
budgettracker/web/templates/layout.html
budgettracker/web/templates/login.html
budgettracker/web/templates/macros.html
budgettracker/web/templates/settings.html
budgettracker/web/templates/transactions_list.html
budgettracker/web/templates/year.html