Metadata-Version: 1.0
Name: budgettracker
Version: 1.6.0
Summary: Simple budget tracking app
Home-page: http://github.com/maximebf/budgettracker
Author: Maxime Bouroumeau-Fuseau
Author-email: maxime.bouroumeau@gmail.com
License: MIT
Platform: any
